getpaths/__init__.py
getpaths-1.0.0.dist-info/LICENSE
getpaths-1.0.0.dist-info/METADATA
getpaths-1.0.0.dist-info/WHEEL
getpaths-1.0.0.dist-info/top_level.txt
getpaths-1.0.0.dist-info/RECORD
