Metadata-Version: 2.1
Name: getpaths
Version: 1.0.0
Summary: Pathing Library
Home-page: https://pypi.org/project/getpaths/
Author: Jv Kyle Eclarin
Author-email: <jvykleeclarin@gmail.com>
License: UNKNOWN
Project-URL: Documentation, https://pypi.org/project/getpaths/
Project-URL: Code, https://github.com/mathemusician/getpath
Project-URL: Issue tracker, https://github.com/mathemusician/getpath/issues
Keywords: python,pathing,path,getpath
Platform: UNKNOWN
Classifier: Development Status :: 3 - Alpha
Classifier: Intended Audience :: Education
Classifier: Programming Language :: Python :: 2
Classifier: Programming Language :: Python :: 3
Classifier: Operating System :: MacOS :: MacOS X
Classifier: Operating System :: Microsoft :: Windows
License-File: LICENSE
